openxps/__init__.py
openxps/_version.py
openxps/biasing_potential.py
openxps/bounds.py
openxps/context.py
openxps/extension_writer.py
openxps/extra_dof.py
openxps/metadynamics.py
openxps/utils.py
openxps/tests/__init__.py
openxps/tests/test_bounds.py
openxps/tests/test_context.py
openxps/tests/test_extension_writer.py
openxps/tests/test_extra_dofs.py
openxps/tests/test_openxps.py
openxps-0.1.0.dist-info/LICENSE.md
openxps-0.1.0.dist-info/METADATA
openxps-0.1.0.dist-info/WHEEL
openxps-0.1.0.dist-info/top_level.txt
openxps-0.1.0.dist-info/RECORD
