Metadata-Version: 2.1
Name: openxps
Version: 0.1.0
Summary: Extended Phase-Space Simulations with OpenMM
Author-email: Charlles Abreu <craabreu@gmail.com>
License: MIT
Classifier: License :: OSI Approved :: MIT License
Classifier: Programming Language :: Python :: 3.9
Classifier: Programming Language :: Python :: 3.10
Classifier: Programming Language :: Python :: 3.11
Classifier: Programming Language :: Python :: 3.12
Requires-Python: >=3.9
License-File: LICENSE.md
Requires-Dist: cvpack
Requires-Dist: numpy
Requires-Dist: openmm
Requires-Dist: pyyaml
Provides-Extra: test
Requires-Dist: pytest >=6.1.2 ; extra == 'test'
Requires-Dist: pytest-runner ; extra == 'test'
